{
  "3D Animation": "تحريك ثلاثي الأبعاد",
  "3D Modeling": "تصميم ثلاثي الأبعاد",
  "A/B Testing": "اختبار A/B",
  "ACLS": "دورة دعم الحياة القلبية المتقدمة",
  "AI Ethics": "أخلاقيات الذكاء الاصطناعي",
  "AI Frameworks": "أُطر الذكاء الاصطناعي",
  "AI Model Training": "تدريب نماذج الذكاء الاصطناعي",
  "AI in Healthcare": "الذكاء الاصطناعي في الرعاية الصحية",
  "AML": "مكافحة غسيل الأموال",
  "API Development": "تطوير واجهات برمجة التطبيقات",
  "AR": "الواقع المعزز",
  "ASD": "اضطراب طيف التوحد",
  "AWS": "خدمات أمازون السحابية",
  "Academic Policy Development": "تطوير السياسات الأكاديمية",
  "Acceptance Testing": "اختبارات القبول",
  "Access Controls": "ضبط الوصول",
  "Account Management": "إدارة الحسابات",
  "Account Planning": "تخطيط الحسابات",
  "Account Reconciliation": "تسوية الحسابات",
  "Active Listening": "الاستماع الفعّال",
  "Activity Analysis": "تحليل الأنشطة",
  "Actuator Design": "تصميم المحركات",
  "Acute Care": "الرعاية الحادة",
  "Adaptability": "المرونة والتأقلم",
  "Adaptive Learning Technologies": "تقنيات التعلم التكيفية",
  "Adaptive Physical Education": "التربية البدنية التكيفية",
  "Administration and Office Support": "الدعم الإداري والمكتبي",
  "Adobe Creative Suite Proficiency": "إتقان حزمة Adobe Creative",
  "Advanced Cardiac Life Support": "دعم الحياة القلبية المتقدم",
  "Advocacy": "الدفاع عن الحقوق",
  "Aerodynamics": "علم الديناميكا الهوائية",
  "Aerospace Engineering": "هندسة الطيران والفضاء",
  "Aerospace Manufacturing": "تصنيع الطيران",
  "Aerospace Materials": "مواد الطيران",
  "Affiliate Marketing": "التسويق بالعمولة",
  "Agile Methodologies": "منهجيات أجايل",
  "Agile and Scrum Methodologies": "منهجيات أجايل وسكرم",
  "Air Pollution Control": "التحكم في تلوث الهواء",
  "Air Quality Analysis": "تحليل جودة الهواء",
  "Aircraft Design": "تصميم الطائرات",
  "Aircraft Maintenance": "صيانة الطائرات",
  "Analytics and Reporting": "التحليلات والتقارير",
  "Animation": "الرسوم المتحركة",
  "Animation Production": "إنتاج الرسوم المتحركة",
  "Animation Techniques": "تقنيات التحريك",
  "Ansible": "أنسبل",
  "Anti-Bribery and Corruption Compliance": "الامتثال لمكافحة الرشوة والفساد",
  "Anti-Money Laundering": "مكافحة غسيل الأموال",
  "Anti-Money Laundering  Policies": "سياسات مكافحة غسيل الأموال",
  "Architectural Rendering": "العرض المعماري",
  "Architecture and Design": "الهندسة المعمارية والتصميم",
  "Art History Knowledge": "معرفة تاريخ الفن",
  "Asset Allocation": "توزيع الأصول",
  "Asset Valuation": "تقييم الأصول",
  "Assistive Technology": "التقنيات المساعدة",
  "Audience Analysis": "تحليل الجمهور",
  "Audience Segmentation": "تقسيم الجمهور",
  "Audio Engineering": "هندسة الصوت",
  "Audit Planning": "تخطيط التدقيق",
  "Audit Reporting": "تقارير التدقيق",
  "Auditing": "التدقيق",
  "Augmented Reality  Content Creation": "إنشاء محتوى للواقع المعزز",
  "Autism Spectrum Disorders": "اضطرابات طيف التوحد",
  "AutoCAD": "أوتوكاد",
  "Automated Decision-Making": "اتخاذ قرارات مؤتمتة",
  "Automated Testing": "الاختبارات المؤتمتة",
  "Automated Testing Tools": "أدوات الاختبار المؤتمتة",
  "Autonomous Systems": "الأنظمة المستقلة",
  "Avionics Systems": "أنظمة الطيران الإلكترونية",
  "Azure": "مايكروسوفت أزور",
  "BIM": "نمذجة معلومات البناء",
  "Bash": "باش",
  "Basic Accounting": "المحاسبة الأساسية",
  "Behavior Management": "إدارة السلوك",
  "Benefits Administration": "إدارة المزايا",
  "Big Data Technologies": "تقنيات البيانات الضخمة",
  "Bioavailability Studies": "دراسات التوافر الحيوي",
  "Biodiversity Monitoring": "مراقبة التنوع البيولوجي",
  "Bioinformatics": "المعلوماتية الحيوية",
  "Biomass Energy Production": "إنتاج الطاقة من الكتلة الحيوية",
  "Biomaterials": "المواد الحيوية",
  "Biomechanics": "الميكانيكا الحيوية",
  "Biomedical Device Design": "تصميم الأجهزة الطبية الحيوية",
  "Biomedical Signal Processing": "معالجة الإشارات الحيوية",
  "Biostatistics": "الإحصاء الحيوي",
  "Blended Learning Models": "نماذج التعلم المدمج",
  "Brand Messaging": "رسائل العلامة التجارية",
  "Brand Perception Analysis": "تحليل انطباع العلامة التجارية",
  "Brand Reputation Management": "إدارة سمعة العلامة التجارية",
  "Branding": "بناء العلامة التجارية",
  "Break-Even Analysis": "تحليل نقطة التعادل",
  "Budget Management": "إدارة الميزانية",
  "Budgeting": "إعداد الميزانية",
  "Budgeting and Forecasting": "التخطيط المالي والتنبؤ",
  "Bug Tracking Systems": "أنظمة تتبع الأخطاء",
  "Building Codes and Regulations": "أنظمة البناء واللوائح",
  "Building Information Modeling": "نمذجة معلومات البناء",
  "Business Case Development": "إعداد دراسات الجدوى",
  "Business Intelligence": "التحليل التجاري",
  "Business Intelligence Tools": "أدوات التحليل التجاري",
   "Business Model Development": "تطوير نموذج العمل",
  "Business Process Improvement": "تحسين العمليات التجارية",
  "Business Proposals": "المقترحات التجارية",
  "Business Strategy": "الاستراتيجية التجارية",
  "Business and Financial Analysis": "التحليل المالي والتجاري",
  "Business and Strategic Planning": "التخطيط الاستراتيجي والتجاري",
  "C++": "سي بلس بلس",
  "CAD Software": "برامج التصميم الهندسي",
  "CAD Software Proficiency": "إتقان برامج CAD",
  "CBT": "العلاج المعرفي السلوكي",
  "CFD": "الديناميكا الهوائية بالحاسوب",
  "CI/CD": "التكامل والتسليم المستمر",
  "CISM": "مدير أمن المعلومات المعتمد",
  "CPT": "الرموز الإجرائية الحالية",
  "CRM": "إدارة علاقات العملاء",
  "CRM Management": "إدارة أنظمة CRM",
  "CRM Software Proficiency": "إتقان برامج CRM",
  "CRO": "تحسين معدل التحويل",
  "CSR": "المسؤولية الاجتماعية للشركات",
  "Calendar Management": "إدارة الجداول الزمنية",
  "Camera Operation": "تشغيل الكاميرات",
  "Campaign Management": "إدارة الحملات",
  "Capacity Planning": "تخطيط السعة",
  "Capital Budgeting": "ميزانية رأس المال",
  "Carbon Emission Reduction": "تقليل انبعاثات الكربون",
  "Carbon Footprint Analysis": "تحليل البصمة الكربونية",
  "Care Plan Development": "تطوير خطة الرعاية",
  "Career Development Planning": "تخطيط تطوير الوظيفة",
  "Case Management": "إدارة الحالات",
  "Cash Flow Analysis": "تحليل التدفق النقدي",
  "Cash Flow Management": "إدارة التدفق النقدي",
  "Ceramic Art": "فن السيراميك",
  "Change Control": "التحكم بالتغييرات",
  "Change Management": "إدارة التغيير",
  "Charitable Giving Strategies": "استراتيجيات التبرع الخيري",
  "Chemical Analysis": "التحليل الكيميائي",
  "Chemical Safety": "السلامة الكيميائية",
  "Child and Adolescent Therapy": "علاج الأطفال والمراهقين",
  "Civil 3D": "برنامج Civil 3D",
  "Classroom Engagement": "تفاعل داخل الصف",
  "Classroom Management": "إدارة الصف",
  "Client Advisory": "استشارات العملاء",
  "Client Counseling": "إرشاد العملاء",
  "Client Needs Analysis": "تحليل احتياجات العميل",
  "Client Relationship Building": "بناء علاقات العملاء",
  "Client Relationship Management": "إدارة علاقات العملاء",
  "Climate Adaptation Strategies": "استراتيجيات التكيّف مع المناخ",
  "Climate Change Mitigation": "التقليل من تغير المناخ",
  "Climate Change Mitigation Strategies": "استراتيجيات التخفيف من تغير المناخ",
  "Clinical Decision Support Systems": "أنظمة دعم القرار السريري",
  "Clinical Documentation": "التوثيق السريري",
  "Clinical Engineering": "الهندسة السريرية",
  "Clinical Nutrition": "التغذية السريرية",
  "Clinical Trials Management": "إدارة التجارب السريرية",
  "Clinical Workflow Optimization": "تحسين سير العمل السريري",
  "Closing Techniques": "تقنيات إغلاق الصفقات",
  "Cloud Computing": "الحوسبة السحابية",
  "Cloud Cost Management": "إدارة تكاليف السحابة",
  "Cloud Infrastructure Management": "إدارة البنية التحتية السحابية",
  "Cloud Migration Strategies": "استراتيجيات نقل البيانات للسحابة",
  "Cloud Networking": "الشبكات السحابية",
  "Cloud Orchestration": "تنظيم الموارد السحابية",
  "Cloud Security": "أمان السحابة",
  "Cloud Service Models": "نماذج خدمات السحابة",
  "Cloud Storage Solutions": "حلول التخزين السحابي",
  "Coaching and Mentoring": "التدريب والإرشاد",
  "Code Review Practices": "ممارسات مراجعة الكود",
  "Code of Conduct Development": "وضع قواعد السلوك",
  "Cognitive Behavioral Therapy": "العلاج السلوكي المعرفي",
  "Cognitive Rehabilitation": "إعادة التأهيل المعرفي",
  "Cold Chain Logistics": "لوجستيات سلسلة التبريد",
  "Collaboration with Families": "التعاون مع العائلات",
  "Color Grading": "تصحيح الألوان",
  "Color Theory": "نظرية الألوان",
  "Communication Skills": "مهارات التواصل",
  "Community Nutrition Programs": "برامج التغذية المجتمعية",
  "Community Outreach": "التواصل المجتمعي",
  "Compensation Strategies": "استراتيجيات التعويض",
  "Competency Mapping": "رسم خريطة المهارات",
  "Competency-Based Education": "التعليم المبني على الكفاءات",
  "Competitive Analysis": "التحليل التنافسي",
  "Competitive Benchmarking": "المقارنة المعيارية التنافسية",
  "Competitive Intelligence": "المعلومات التنافسية",
  "Competitive Strategy": "الاستراتيجية التنافسية",
  "Compliance Auditing": "تدقيق الامتثال",
  "Compliance Audits": "مراجعة الامتثال",
  "Compliance Monitoring": "مراقبة الامتثال",
  "Compliance Reporting": "تقارير الامتثال",
  "Compliance Risk Assessment": "تقييم مخاطر الامتثال",
  "Compliance Training": "تدريب على الامتثال",
  "Compliance Training Programs": "برامج تدريب الامتثال",
  "Compliance with Employment Laws": "الامتثال لقوانين العمل",
  "Computational Fluid Dynamics": "الديناميكا الحوسبية للسوائل",
  "Computer Vision": "رؤية الحاسوب",
  "Concept Development": "تطوير المفاهيم",
  "Conceptual Art": "الفن المفاهيمي",
  "Confidentiality": "السرية",
  "Confidentiality Agreements": "اتفاقيات السرية",
  "Configuration Management": "إدارة الإعدادات",
  "Conflict Resolution": "حل النزاعات", "Conservation Education": "توعية بيئية",
  "Conservation Planning": "تخطيط الحماية البيئية",
  "Conservation Policy": "سياسات الحماية البيئية",
  "Conservation Program Management": "إدارة برامج الحفظ",
  "Conservation Techniques": "تقنيات الحماية",
  "Construction Documentation": "توثيق أعمال البناء",
  "Construction Management": "إدارة المشاريع الإنشائية",
  "Consultative Selling": "البيع الاستشاري",
  "Consulting Methodologies": "منهجيات الاستشارات",
  "Consumer Behavior Analysis": "تحليل سلوك المستهلك",
  "Container Management": "إدارة الحاويات",
  "Containerization": "تحزيم الحاويات",
  "Content Calendars": "جداول المحتوى",
  "Content Creation": "إنشاء المحتوى",
  "Content Curation": "تنسيق المحتوى",
  "Content Distribution": "توزيع المحتوى",
  "Content Marketing": "تسويق المحتوى",
  "Content Performance Analysis": "تحليل أداء المحتوى",
  "Continuous Integration/Continuous Deployment": "الدمج والتسليم المستمر",
  "Contract Compliance Monitoring": "مراقبة الامتثال للعقود",
  "Contract Dispute Resolution": "حل نزاعات العقود",
  "Contract Drafting": "صياغة العقود",
  "Contract Drafting and Negotiation": "صياغة وتفاوض العقود",
  "Contract Law": "قانون العقود",
  "Contract Lifecycle Management": "إدارة دورة حياة العقد",
  "Contract Management Software": "برامج إدارة العقود",
  "Contract Negotiation": "تفاوض العقود",
  "Control Systems": "أنظمة التحكم",
  "Conversion Rate Optimization": "تحسين معدل التحويل",
  "Copyright Law": "قانون حقوق النشر",
  "Copywriting": "كتابة الإعلانات",
  "Corporate Compliance Programs": "برامج الامتثال المؤسسي",
  "Corporate Governance": "حوكمة الشركات",
  "Corporate Law": "القانون التجاري",
  "Corporate Social Responsibility": "المسؤولية الاجتماعية للشركات",
  "Cost Accounting": "محاسبة التكاليف",
  "Cost Analysis": "تحليل التكاليف",
  "Cost Control": "التحكم بالتكاليف",
  "Cost Estimation": "تقدير التكاليف",
  "Cost-Benefit Analysis": "تحليل التكلفة مقابل الفائدة",
  "Course Evaluation Techniques": "طرق تقييم الدورات",
  "Creative Concept Development": "تطوير المفاهيم الإبداعية",
  "Creative and Design": "الإبداع والتصميم",
  "Creative and Digital Media": "الإبداع والإعلام الرقمي",
  "Creative and Multimedia": "الإبداع والوسائط المتعددة",
  "Creative and Multimedia Production": "إنتاج الوسائط المتعددة الإبداعية",
  "Creative and Visual Arts": "الإبداع والفنون البصرية",
  "Credit Risk Management": "إدارة مخاطر الائتمان",
  "Crisis Communication": "الاتصال وقت الأزمات",
  "Crisis Intervention": "التدخل في الأزمات",
  "Crisis Management": "إدارة الأزمات",
  "Critical Incident Stress Management": "إدارة الإجهاد الناتج عن الحوادث الحرجة",
  "Cross-Docking Operations": "عمليات النقل المتقاطع",
  "Cross-Functional Collaboration": "التعاون بين الفرق المختلفة",
  "Cross-Selling": "البيع المتقاطع",
  "Cultural Transformation": "التحول الثقافي",
  "Curriculum Development": "تطوير المناهج",
  "Curriculum Mapping": "رسم خريطة المناهج",
  "Customer Advocacy": "دعم العملاء",
  "Customer Insights": "رؤى العملاء",
  "Customer Journey Analysis": "تحليل رحلة العميل",
  "Customer Journey Mapping": "رسم رحلة العميل",
  "Customer Loyalty Programs": "برامج ولاء العملاء",
  "Customer Needs Analysis": "تحليل احتياجات العملاء",
  "Customer Onboarding": "إدخال العملاء الجدد",
  "Customer Onboarding Processes": "عمليات دمج العملاء الجدد",
  "Customer Relationship Management": "إدارة علاقات العملاء",
  "Customer Retention": "الاحتفاظ بالعملاء",
  "Customer Retention Strategies": "استراتيجيات الاحتفاظ بالعملاء",
  "Customer Satisfaction Metrics": "مقاييس رضا العملاء",
  "Customer Segmentation": "تقسيم العملاء",
  "Customer Service": "خدمة العملاء",
  "Customer Service and Support": "خدمة ودعم العملاء",
  "Cyber Forensics": "الأدلة الجنائية السيبرانية",
  "Cybersecurity": "الأمن السيبراني",
  "Cybersecurity Standards": "معايير الأمن السيبراني",
  "Data Analysis": "تحليل البيانات",
  "Data Architecture": "هندسة البيانات",
  "Data Cleaning": "تنظيف البيانات",
  "Data Cleaning and Preparation": "تنظيف وتحضير البيانات",
  "Data Encryption": "تشفير البيانات",
  "Data Entry": "إدخال البيانات",
  "Data Governance": "حوكمة البيانات",
  "Data Interpretation": "تفسير البيانات",
  "Data Mining": "تنقيب البيانات",
  "Data Privacy": "خصوصية البيانات",
  "Data Privacy Regulations": "أنظمة خصوصية البيانات",
  "Data Privacy in Healthcare": "خصوصية البيانات في الرعاية الصحية",
  "Data Protection Compliance": "الامتثال لحماية البيانات",
  "Data Science Programming": "برمجة علوم البيانات",
  "Data Security Practices": "ممارسات أمان البيانات",
  "Data Structures and Algorithms": "هياكل البيانات والخوارزميات",
  "Data Visualization": "تصوير البيانات",
  "Data Visualization Techniques": "تقنيات عرض البيانات",
  "Data Warehousing": "مخازن البيانات",
  "Database Management": "إدارة قواعد البيانات",
  "Database Querying": "استعلام قواعد البيانات",
  "Debt Management": "إدارة الديون",
  "Debugging and Troubleshooting": "إصلاح الأخطاء وحل المشاكل",
  "Deep Learning": "التعلم العميق","Defect Management": "إدارة العيوب",
  "Demand Analysis": "تحليل الطلب",
  "Demand Forecasting": "توقع الطلب",
  "Demand Planning": "تخطيط الطلب",
  "Derivatives Trading": "تداول المشتقات",
  "DevOps Tools": "أدوات ديف أوبس",
  "DevOps in Cloud": "ديف أوبس في السحابة",
  "Diet Planning": "تخطيط النظام الغذائي",
  "Dietary Supplement Knowledge": "معرفة المكملات الغذائية",
  "Differentiated Instruction": "التعليم التفريقي",
  "Digital Advertising": "الإعلانات الرقمية",
  "Digital Art": "الفن الرقمي",
  "Digital Content Delivery": "توصيل المحتوى الرقمي",
  "Digital Illustration": "الرسوم التوضيحية الرقمية",
  "Digital Marketing": "التسويق الرقمي",
  "Digital Photography": "التصوير الرقمي",
  "Digital Storytelling": "السرد الرقمي",
  "Disaster Preparedness": "الاستعداد للكوارث",
  "Disaster Recovery": "استعادة البيانات بعد الكوارث",
  "Disaster Recovery Planning": "تخطيط استعادة البيانات",
  "Dispute Resolution": "حل النزاعات",
  "Distance Education Strategies": "استراتيجيات التعليم عن بعد",
  "Distribution Network Design": "تصميم شبكات التوزيع",
  "Distribution Strategy": "استراتيجية التوزيع",
  "Diversity Training": "تدريب على التنوع",
  "Diversity and Inclusion": "التنوع والشمول",
  "Diversity and Inclusion Initiatives": "مبادرات التنوع والشمول",
  "Docker": "دوكر",
  "Document Preparation": "تحضير الوثائق",
  "Document Review": "مراجعة الوثائق",
  "Documentary Filmmaking": "إنتاج الأفلام الوثائقية",
  "Documentation Management": "إدارة الوثائق",
  "Documentation and Reporting": "التوثيق والتقارير",
  "Drawing and Sketching": "الرسم والتخطيط",
  "Drug Delivery Systems": "أنظمة توصيل الأدوية",
  "Drug Development Process": "عملية تطوير الدواء",
  "Drug Safety Assessment": "تقييم سلامة الدواء",
  "Due Diligence": "العناية الواجبة",
  "E-Learning Platforms": "منصات التعليم الإلكتروني",
  "E-book Creation": "إنشاء الكتب الإلكترونية",
  "E-commerce Analytics": "تحليلات التجارة الإلكترونية",
  "E-learning Design": "تصميم التعليم الإلكتروني",
  "E-learning Development": "تطوير التعليم الإلكتروني",
  "EAP": "برنامج مساعدة الموظفين",
  "EHR": "السجلات الصحية الإلكترونية",
  "EHS": "الصحة والسلامة والبيئة",
  "EMS": "خدمات الطوارئ الطبية",
  "ERM": "إدارة المخاطر المؤسسية",
  "ETL Processes": "عمليات الاستخراج والتحويل والتحميل",
  "Early Intervention Strategies": "استراتيجيات التدخل المبكر",
  "Ecological Restoration": "استعادة النظام البيئي",
  "Economic Analysis": "التحليل الاقتصادي",
  "Ecosystem Management": "إدارة النظام البيئي",
  "Ecosystem Restoration": "إعادة تأهيل النظام البيئي",
  "Editorial Strategy": "استراتيجية التحرير",
  "Education Savings Plans": "خطط توفير التعليم",
  "Education and Consulting": "التعليم والاستشارات",
  "Education and Curriculum Development": "التعليم وتطوير المناهج",
  "Education and Online Learning": "التعليم والتعلم عبر الإنترنت",
  "Education and Special Education": "التعليم والتعليم الخاص",
  "Education and Teaching": "التعليم والتدريس",
  "Educational Assessment": "التقييم التربوي",
  "Educational Gamification": "التلعيب في التعليم",
  "Educational Leadership": "القيادة التعليمية",
  "Educational Program Design": "تصميم البرامج التعليمية",
  "Educational Psychology": "علم النفس التربوي",
  "Educational Research": "البحث التربوي",
  "Educational Standards Alignment": "موازاة المعايير التعليمية",
  "Educational Technology": "تقنيات التعليم",
  "Electrical Systems Design": "تصميم الأنظمة الكهربائية",
  "Electronic Health Records": "السجلات الصحية الإلكترونية",
  "Electrotherapy": "العلاج الكهربائي",
  "Email Campaigns": "حملات البريد الإلكتروني",
  "Email Management": "إدارة البريد الإلكتروني",
  "Email Marketing": "التسويق عبر البريد الإلكتروني",
  "Embedded Systems": "الأنظمة المدمجة",
  "Emergency Medical Procedures": "إجراءات الطوارئ الطبية",
  "Emergency Medical Services  Coordination": "تنسيق خدمات الطوارئ الطبية",
  "Emergency Preparedness": "الجاهزية للطوارئ",
  "Emergency Response": "الاستجابة للطوارئ",
  "Emergency Response Planning": "تخطيط الاستجابة للطوارئ",
  "Empathy": "التعاطف",
  "Employee Assistance Programs": "برامج دعم الموظفين",
  "Employee Development Plans": "خطط تطوير الموظفين",
  "Employee Engagement Strategies": "استراتيجيات تفاعل الموظفين",
  "Employee Feedback Mechanisms": "آليات التغذية الراجعة للموظفين",
  "Employee Motivation Strategies": "استراتيجيات تحفيز الموظفين",
  "Employee Onboarding": "إدماج الموظفين الجدد",
  "Employee Relations": "علاقات الموظفين",
  "Employee Relations Counseling": "إرشاد علاقات الموظفين",
  "Employee Retention": "الاحتفاظ بالموظفين",
  "Employee Retention Strategies": "استراتيجيات الحفاظ على الموظفين",
  "Employee Satisfaction Surveys": "استبيانات رضا الموظفين",
  "Employee Survey Analysis": "تحليل استبيانات الموظفين",
  "Employee Wellbeing Programs": "برامج رفاه الموظفين",
  "Employment Contracts": "عقود التوظيف",
  "Employment Law": "قانون العمل",
  "Energy Efficiency Audits": "تدقيق كفاءة الطاقة",
  "Energy Modeling and Simulation": "نمذجة الطاقة والمحاكاة",
  "Energy Storage Solutions": "حلول تخزين الطاقة","Engineering and Civil Engineering": "الهندسة والهندسة المدنية",
  "Engineering and Manufacturing": "الهندسة والتصنيع",
  "Engineering and Robotics": "الهندسة والروبوتات",
  "Enterprise Architecture": "هندسة المؤسسة",
  "Enterprise Risk Management": "إدارة مخاطر المؤسسات",
  "Environmental Education": "التوعية البيئية",
  "Environmental Education Programs": "برامج التعليم البيئي",
  "Environmental Health": "الصحة البيئية",
  "Environmental Health Risk Assessment": "تقييم مخاطر الصحة البيئية",
  "Environmental Health and Safety": "الصحة والسلامة البيئية",
  "Environmental Impact Assessment": "تقييم الأثر البيئي",
  "Environmental Impact Assessments": "تقييمات الأثر البيئي",
  "Environmental Impact Monitoring": "مراقبة الأثر البيئي",
  "Environmental Impact Reporting": "تقرير الأثر البيئي",
  "Environmental Legislation": "التشريعات البيئية",
  "Environmental Policy": "السياسات البيئية",
  "Environmental Policy Analysis": "تحليل السياسات البيئية",
  "Environmental Regulations Compliance": "الامتثال للأنظمة البيئية",
  "Environmental Risk Assessment": "تقييم المخاطر البيئية",
  "Environmental Science and Conservation": "علوم البيئة والحفاظ عليها",
  "Environmental Science and Sustainability": "علوم البيئة والاستدامة",
  "Equity Research": "بحوث الأسهم",
  "Ergonomic Assessments": "تقييمات مريحة للجسم",
  "Ergonomics": "بيئة العمل المريحة",
  "Estate Planning": "تخطيط الإرث",
  "Ethics Investigations": "تحقيقات أخلاقية",
  "Ethics Training Programs": "برامج تدريب على الأخلاقيات",
  "Ethics in Government": "الأخلاقيات في الحكومة",
  "Ethics in Healthcare": "الأخلاقيات في الرعاية الصحية",
  "Event Planning": "تنظيم الفعاليات",
  "Exit Interviews": "مقابلات الخروج",
  "Experiment Design": "تصميم التجارب",
  "FDA Regulations": "أنظمة هيئة الغذاء والدواء",
  "FHIR": "معيار FHIR للسجلات الطبية",
  "Faculty Development": "تطوير أعضاء الهيئة التدريسية",
  "Family Therapy": "العلاج الأسري",
  "Feature Prioritization": "تحديد أولويات الميزات",
  "Feedback Handling": "التعامل مع الملاحظات",
  "Field Triage": "فرز الحالات في الميدان",
  "Filing and Organization": "التنظيم والأرشفة",
  "Finance and Accounting": "التمويل والمحاسبة",
  "Finance and Financial Planning": "التمويل والتخطيط المالي",
  "Finance and Investment Banking": "التمويل والبنوك الاستثمارية",
  "Finance and Risk Management": "التمويل وإدارة المخاطر",
  "Finance and Wealth Management": "التمويل وإدارة الثروات",
  "Financial Analysis": "التحليل المالي",
  "Financial Benchmarking": "المقارنة المالية المرجعية",
  "Financial Forecasting": "التنبؤ المالي",
  "Financial Goal Setting": "تحديد الأهداف المالية",
  "Financial Literacy Education": "التثقيف المالي",
  "Financial Market Analysis": "تحليل الأسواق المالية",
  "Financial Markets Analysis": "تحليل أسواق المال",
  "Financial Modeling": "النمذجة المالية",
  "Financial Planning": "التخطيط المالي",
  "Financial Ratio Analysis": "تحليل النسب المالية",
  "Financial Reporting": "التقارير المالية",
  "Financial Risk Modeling": "نمذجة المخاطر المالية",
  "Financial Statement Analysis": "تحليل القوائم المالية",
  "Firewall Configuration": "إعداد الجدار الناري",
  "Firewalls and VPNs": "الجدران النارية والشبكات الخاصة",
  "First Responder Training": "تدريب المستجيبين الأوائل",
  "Fixed Income Analysis": "تحليل الدخل الثابت",
  "Fleet Management": "إدارة الأسطول",
  "Flight Testing": "اختبارات الطيران",
  "Focus Group Facilitation": "تيسير مجموعات التركيز",
  "Food Safety": "سلامة الغذاء",
  "Forest Management": "إدارة الغابات",
  "Formulation Development": "تطوير التركيبات",
  "Fraud Detection": "كشف الاحتيال",
  "Freight Management": "إدارة الشحن",
  "Functional Testing": "الاختبار الوظيفي",
  "GDPR": "اللائحة العامة لحماية البيانات",
  "GIS Mapping": "رسم الخرائط الجغرافية",
  "GMP": "ممارسات التصنيع الجيد",
  "Gait Training": "تدريب على المشي",
  "Genetic Engineering": "الهندسة الوراثية",
  "Geotechnical Engineering": "الهندسة الجيوتقنية",
  "Geothermal Energy Systems": "أنظمة الطاقة الحرارية الأرضية",
  "Geriatric Mental Health": "الصحة النفسية للمسنين",
  "Geriatric Nursing": "التمريض للمسنين",
  "Geriatric Occupational Therapy": "العلاج الوظيفي لكبار السن",
  "Git": "جيت",
  "Global Logistics": "الخدمات اللوجستية العالمية",
  "Go-to-Market Strategy": "استراتيجية دخول السوق",
  "Good Manufacturing Practices": "ممارسات التصنيع الجيدة",
  "Google Analytics": "تحليلات جوجل",
  "Government Relations": "العلاقات الحكومية",
  "Government and Policy Analysis": "تحليل السياسات الحكومية",
  "Grant Writing": "كتابة طلبات المنح",
  "Graphic Art": "الفن الجرافيكي",
  "Graphic Design": "التصميم الجرافيكي",
  "Green Building Design": "تصميم المباني الخضراء",
  "Green Screen Techniques": "تقنيات الشاشة الخضراء",
  "Green Technology Innovation": "ابتكارات التقنية الخضراء",
  "Grievance Handling": "التعامل مع الشكاوى",
  "Group Therapy": "العلاج الجماعي",
  "Group Therapy Facilitation": "تيسير جلسات العلاج الجماعي",
  "Growth Strategy": "استراتيجية النمو",
  "HIE": "تبادل المعلومات الصحية","HNI": "إدارة العملاء ذوي الثروات العالية",
  "HR Analytics": "تحليلات الموارد البشرية",
  "HR Compliance": "امتثال الموارد البشرية",
  "HR Policy Development": "تطوير سياسات الموارد البشرية",
  "HRIS Systems": "أنظمة معلومات الموارد البشرية",
  "Habitat Management": "إدارة المواطن البيئية",
  "Habitat Restoration": "إعادة تأهيل المواطن البيئية",
  "Hadoop": "هيدوب",
  "Hand Therapy": "علاج اليد",
  "Hazard Analysis": "تحليل المخاطر",
  "Hazardous Materials Management": "إدارة المواد الخطرة",
  "Health Data Analytics": "تحليل بيانات الصحة",
  "Health Education": "التثقيف الصحي",
  "Health IT Security": "أمن تكنولوجيا المعلومات الصحية",
  "Health Informatics Standards": "معايير المعلومات الصحية",
  "Health Information Exchange": "تبادل المعلومات الصحية",
  "Health Information Systems": "أنظمة المعلومات الصحية",
  "Health Policy Analysis": "تحليل السياسات الصحية",
  "Health and Safety Management": "إدارة الصحة والسلامة",
  "Healthcare IT Project Management": "إدارة مشاريع تكنولوجيا المعلومات في الصحة",
  "Healthcare and Biomedical Engineering": "الرعاية الصحية والهندسة الطبية الحيوية",
  "Healthcare and Emergency Medicine": "الرعاية الصحية والطب الطارئ",
  "Healthcare and Health Informatics": "الرعاية الصحية والمعلوماتية الصحية",
  "Healthcare and Mental Health": "الرعاية الصحية والصحة النفسية",
  "Healthcare and Nursing": "الرعاية الصحية والتمريض",
  "Healthcare and Nutrition": "الرعاية الصحية والتغذية",
  "Healthcare and Occupational Therapy": "الرعاية الصحية والعلاج الوظيفي",
  "Healthcare and Pharmaceutical Sciences": "الرعاية الصحية والعلوم الصيدلانية",
  "Healthcare and Physical Therapy": "الرعاية الصحية والعلاج الطبيعي",
  "Healthcare and Regulatory Affairs": "الرعاية الصحية والشؤون التنظيمية",
  "Hedge Fund Management": "إدارة صناديق التحوط",
  "High Net-Worth Individual  Management": "إدارة الأفراد ذوي الثروات العالية",
  "Historic Preservation": "الحفاظ على التراث",
  "Holistic Nutrition": "التغذية الشمولية",
  "Home Modifications": "تعديلات على المنزل",
  "Human Resources and Employee Engagement": "الموارد البشرية وتفاعل الموظفين",
  "Human Resources and Employee Relations": "الموارد البشرية وعلاقات الموظفين",
  "Human Resources and Organizational Development": "الموارد البشرية وتطوير المؤسسات",
  "Human Resources and Recruitment": "الموارد البشرية والتوظيف",
  "Human Resources and Training": "الموارد البشرية والتدريب",
  "Human-Robot Interaction": "تفاعل الإنسان والروبوت",
  "Hydraulic Engineering": "الهندسة الهيدروليكية",
  "Hydrotherapy": "العلاج بالماء",
  "Hypothesis Testing": "اختبار الفرضيات",
  "IAM": "إدارة الهوية والوصول",
  "ICD-10": "التصنيف الدولي للأمراض - الإصدار العاشر",
  "IDS": "أنظمة كشف التسلل",
  "IEP": "برامج التعليم الفردي",
  "IP Due Diligence": "العناية الواجبة في الملكية الفكرية",
  "IP Litigation": "قضايا الملكية الفكرية",
  "IP Portfolio Management": "إدارة محفظة الملكية الفكرية",
  "IP Risk Management": "إدارة مخاطر الملكية الفكرية",
  "IP Strategy Development": "تطوير استراتيجية الملكية الفكرية",
  "IP Valuation": "تقييم الملكية الفكرية",
  "ISO 27001": "المعيار الدولي ISO 27001 لأمن المعلومات",
  "IT General Controls": "الضوابط العامة لتقنية المعلومات",
  "IT Governance": "حوكمة تكنولوجيا المعلومات",
  "IT Infrastructure": "البنية التحتية لتكنولوجيا المعلومات",
  "IT Risk Management": "إدارة مخاطر تكنولوجيا المعلومات",
  "ITGC": "الضوابط العامة لتكنولوجيا المعلومات",
  "IV Therapy": "العلاج الوريدي",
  "IaC": "البنية التحتية ككود",
  "IaaS": "البنية التحتية كخدمة",
  "Identity and Access Management": "إدارة الهوية والوصول",
  "Illustration": "الرسم التوضيحي",
  "Import/Export Regulations": "أنظمة الاستيراد والتصدير",
  "Incident Investigation": "التحقيق في الحوادث",
  "Incident Response": "الاستجابة للحوادث",
  "Inclusive Education Practices": "ممارسات التعليم الشامل",
  "Individualized Education Programs": "برامج التعليم الفردي",
  "Industrial Automation": "الأتمتة الصناعية",
  "Industrial Hygiene": "الصحة الصناعية",
  "Industry-Specific Compliance": "الامتثال حسب القطاع",
  "Infection Control": "مكافحة العدوى",
  "Influencer Collaboration": "التعاون مع المؤثرين",
  "Influencer Engagement": "تفاعل المؤثرين",
  "Influencer Marketing": "تسويق المؤثرين",
  "Influencer Partnerships": "شراكات مع المؤثرين",
  "Infographic Design": "تصميم الإنفوجرافيك",
  "Information Technology and Artificial Intelligence": "تكنولوجيا المعلومات والذكاء الاصطناعي",
  "Information Technology and Auditing": "تكنولوجيا المعلومات والتدقيق",
  "Information Technology and Cloud Computing": "تكنولوجيا المعلومات والحوسبة السحابية",
  "Information Technology and Cybersecurity": "تكنولوجيا المعلومات والأمن السيبراني",
  "Information Technology and Data Analysis": "تكنولوجيا المعلومات وتحليل البيانات",
  "Information Technology and Data Science": "تكنولوجيا المعلومات وعلوم البيانات",
  "Information Technology and DevOps": "تكنولوجيا المعلومات وديف أوبس",
  "Information Technology and Engineering": "تكنولوجيا المعلومات والهندسة",
  "Information Technology and Network Administration": "تكنولوجيا المعلومات وإدارة الشبكات",
  "Information Technology and Software Testing": "تكنولوجيا المعلومات واختبار البرمجيات",
  "Infrastructure Design": "تصميم البنية التحتية",
  "Infrastructure as Code": "البنية التحتية ككود",
  "Innovation Management": "إدارة الابتكار",
  "Instructional Design": "تصميم التعليم",
  "Instructional Materials Development": "تطوير المواد التعليمية",
  "Instructional Strategies": "استراتيجيات التعليم",
  "Insurance Planning": "تخطيط التأمين",
  "Insurance Risk Management": "إدارة مخاطر التأمين",
  "Integration Testing": "اختبار التكامل",
  "Intellectual Property Contracts": "عقود الملكية الفكرية",
  "Intellectual Property Law": "قانون الملكية الفكرية","Intellectual Property Licensing": "ترخيص الملكية الفكرية",
  "Interactive Learning Tools": "أدوات تعليم تفاعلية",
  "Interactive Media": "وسائط تفاعلية",
  "Internal Communications": "الاتصال الداخلي",
  "Internal Controls": "الضوابط الداخلية",
  "Internal Investigations": "التحقيقات الداخلية",
  "International Contracts": "العقود الدولية",
  "International IP Law": "قانون الملكية الفكرية الدولي",
  "Interoperability in Healthcare": "تكامل الأنظمة في الرعاية الصحية",
  "Intrusion Detection Systems": "أنظمة كشف التسلل",
  "Inventory Accuracy": "دقة المخزون",
  "Inventory Control": "مراقبة المخزون",
  "Inventory Control Systems": "أنظمة إدارة المخزون",
  "Inventory Forecasting": "توقع المخزون",
  "Inventory Optimization": "تحسين إدارة المخزون",
  "Investment Advising": "استشارات استثمارية",
  "Investment Appraisal": "تقييم الاستثمار",
  "Investment Portfolio Management": "إدارة محفظة الاستثمار",
  "Investment Strategies": "استراتيجيات الاستثمار",
  "JIT": "الإنتاج حسب الطلب (JIT)",
  "Java": "جافا",
  "Jenkins": "جينكنز",
  "Just-in-Time  Inventory": "المخزون حسب الطلب",
  "Key Account Management": "إدارة الحسابات الرئيسية",
  "Kinematics": "الحركيات",
  "Kubernetes": "كوبرنيتس",
  "LMS": "أنظمة إدارة التعلم",
  "Lab Safety Protocols": "إجراءات السلامة في المختبر",
  "Labeling Compliance": "الامتثال في وضع العلامات",
  "Labor Relations": "علاقات العمل",
  "Laboratory Techniques": "تقنيات المختبر",
  "Landscape Architecture": "هندسة المناظر الطبيعية",
  "Lead Generation": "توليد العملاء المحتملين",
  "Lead Qualification": "تأهيل العملاء المحتملين",
  "Leadership": "القيادة",
  "Leadership Development": "تطوير القيادة",
  "Leadership Training": "تدريب على القيادة",
  "Lean Manufacturing": "التصنيع الرشيق",
  "Lean Supply Chain": "سلسلة التوريد الرشيقة",
  "Lean Warehousing": "المخازن الرشيقة",
  "Learning Assessment Tools": "أدوات تقييم التعلم",
  "Learning Disabilities": "صعوبات التعلم",
  "Learning Management Systems": "أنظمة إدارة التعلم",
  "Learning Outcomes Assessment": "تقييم نتائج التعلم",
  "Learning Theories": "نظريات التعلم",
  "Legal Documentation": "الوثائق القانونية",
  "Legal Drafting": "الصياغة القانونية",
  "Legal Research": "البحث القانوني",
  "Legal Risk Assessment": "تقييم المخاطر القانونية",
  "Legal Writing": "الكتابة القانونية",
  "Legal and Compliance": "القانون والامتثال",
  "Legal and Contract Management": "القانون وإدارة العقود",
  "Legal and Corporate Compliance": "القانون والامتثال المؤسسي",
  "Legal and Corporate Law": "القانون التجاري والمؤسسي",
  "Legal and Intellectual Property": "القانون والملكية الفكرية",
  "Legislative Processes": "العمليات التشريعية",
  "Lesson Plan Development": "تطوير خطط الدروس",
  "Lesson Planning": "تخطيط الدروس",
  "Licensing Agreements": "اتفاقيات الترخيص",
  "Lighting Design": "تصميم الإضاءة",
  "Litigation Support": "دعم التقاضي",
  "Load Testing": "اختبار التحميل",
  "Logistics Coordination": "تنسيق اللوجستيات",
  "Logistics Cost Analysis": "تحليل تكلفة اللوجستيات",
  "Logistics Planning": "تخطيط اللوجستيات",
  "Logistics Software": "برمجيات اللوجستيات",
  "Logistics and Supply Chain Management": "إدارة اللوجستيات وسلسلة التوريد",
  "Logistics and Supply Chain Planning": "تخطيط سلسلة التوريد واللوجستيات",
  "Logistics and Transportation Management": "إدارة النقل واللوجستيات",
  "Logistics and Warehouse Management": "إدارة المستودعات واللوجستيات",
  "M&A": "الاندماج والاستحواذ",
  "MOOC Development": "تطوير دورات الموك",
  "Machine Learning Algorithms": "خوارزميات تعلم الآلة",
  "Machine Learning Models": "نماذج تعلم الآلة",
  "Machine Vision": "رؤية الآلة",
  "Manual Testing Techniques": "تقنيات الاختبار اليدوي",
  "Manual Therapy": "العلاج اليدوي",
  "Marine Conservation": "حماية الحياة البحرية",
  "Market Analysis": "تحليل السوق",
  "Market Entry Strategies": "استراتيجيات دخول السوق",
  "Market Forecasting": "توقعات السوق",
  "Market Penetration": "اختراق السوق",
  "Market Research": "أبحاث السوق",
  "Market Risk Analysis": "تحليل مخاطر السوق",
  "Market Trend Analysis": "تحليل اتجاهات السوق",
  "Marketing Automation": "أتمتة التسويق",
  "Marketing and Communications": "التسويق والاتصالات",
  "Marketing and Content Strategy": "استراتيجية التسويق بالمحتوى",
  "Marketing and Digital Marketing": "التسويق الرقمي",
  "Marketing and Public Relations": "التسويق والعلاقات العامة",
  "Material Science": "علم المواد",
  "Materials Science": "علوم المواد",
  "Mechanical Systems Design": "تصميم الأنظمة الميكانيكية",
  "Media Encoding": "ترميز الوسائط",
  "Media Relations": "علاقات إعلامية",
  "Media Training": "تدريب إعلامي",
  "Mediation and Arbitration": "الوساطة والتحكيم",
  "Medical Coding and Classification Systems": "أنظمة الترميز الطبي والتصنيف",
  "Medical Device Testing": "اختبار الأجهزة الطبية",
  "Medical Imaging": "التصوير الطبي","Medical Nutrition Therapy": "العلاج الغذائي الطبي",
  "Medical Writing": "الكتابة الطبية",
  "Medication Administration": "إعطاء الأدوية",
  "Meeting Coordination": "تنسيق الاجتماعات",
  "Mental Health Assessment": "تقييم الصحة النفسية",
  "Mental Health Interventions": "تدخلات الصحة النفسية",
  "Mergers and Acquisitions": "الاندماج والاستحواذ",
  "Mergers and Acquisitions Agreements": "اتفاقيات الاندماج والاستحواذ",
  "Microscopy": "علم المجهر",
  "Mixed Media": "وسائط متعددة مختلطة",
  "Mobile Marketing": "التسويق عبر الجوال",
  "Molecular Biology Techniques": "تقنيات علم الأحياء الجزيئي",
  "Monitoring and Logging": "المراقبة وتسجيل الأحداث",
  "Motion Graphics": "الرسوم المتحركة",
  "Motion Planning": "تخطيط الحركة",
  "Multi-Cloud Management": "إدارة السُحب المتعددة",
  "Multimedia Editing": "تحرير الوسائط المتعددة",
  "Multitasking": "تعدد المهام",
  "Mutual Funds": "الصناديق المشتركة",
  "NLP": "معالجة اللغة الطبيعية",
  "Nanotechnology": "تقنية النانو",
  "Natural Language Processing": "معالجة اللغة الطبيعية",
  "Navigation Systems": "أنظمة الملاحة",
  "Needs Assessment": "تقييم الاحتياجات",
  "Negotiation": "التفاوض",
  "Negotiation Skills": "مهارات التفاوض",
  "Network Configuration": "إعداد الشبكات",
  "Network Design": "تصميم الشبكات",
  "Network Security": "أمن الشبكات",
  "Network Troubleshooting": "استكشاف مشاكل الشبكة",
  "Networking": "بناء العلاقات",
  "Networking Skills": "مهارات التواصل والعلاقات",
  "Neural Networks": "الشبكات العصبية",
  "Neurological Rehabilitation": "التأهيل العصبي",
  "NoSQL": "قواعد البيانات NoSQL",
  "Nutrigenomics": "علم تغذية الجينات",
  "Nutritional Assessment": "تقييم التغذية",
  "Nutritional Counseling": "الإرشاد الغذائي",
  "Nutritional Research": "البحث الغذائي",
  "OOD": "تصميم موجه للكائنات",
  "Object-Oriented Design": "تصميم موجه للكائنات",
  "Occupational Health": "الصحة المهنية",
  "Occupational Health and Safety": "الصحة والسلامة المهنية",
  "Occupational Therapy Assessments": "تقييمات العلاج الوظيفي",
  "Office Management": "إدارة المكاتب",
  "Onboarding Programs": "برامج إدماج الموظفين",
  "Online Assessments": "الاختبارات الإلكترونية",
  "Online Course Creation": "إنشاء دورات إلكترونية",
  "Online Discussion Facilitation": "تيسير النقاشات عبر الإنترنت",
  "Online Reputation Management": "إدارة السمعة على الإنترنت",
  "Online Student Engagement": "تفاعل الطلاب عبر الإنترنت",
  "Operational Analysis": "التحليل التشغيلي",
  "Operational Risk Management": "إدارة المخاطر التشغيلية",
  "Operations and Management": "العمليات والإدارة",
  "Orchestration": "تنسيق الأنظمة والعمليات",
  "Order Fulfillment": "تنفيذ الطلبات",
  "Order Fulfillment Processes": "عمليات تنفيذ الطلبات",
  "Organizational Behavior": "سلوك المنظمات",
  "Organizational Design": "تصميم الهيكل التنظيمي",
  "Organizational Effectiveness": "فعالية المنظمة",
  "Organizational Strategy": "الاستراتيجية التنظيمية",
  "Orthopedic Knowledge": "معرفة في طب العظام",
  "PALS": "دعم الحياة للأطفال المتقدم",
  "PPC": "الدفع مقابل النقرة",
  "PPE": "معدات الحماية الشخصية",
  "PR Metrics and Analytics": "تحليلات العلاقات العامة",
  "PaaS": "المنصة كخدمة",
  "Pain Management": "إدارة الألم",
  "Painting": "الرسم",
  "Parent-Teacher Communication": "التواصل بين الأهل والمعلمين",
  "Patent Law": "قانون البراءات",
  "Patent Prosecution": "إجراءات البراءات",
  "Patience": "الصبر",
  "Patient Advocacy": "الدفاع عن المرضى",
  "Patient Assessment": "تقييم حالة المريض",
  "Patient Care": "رعاية المرضى",
  "Patient Counseling": "إرشاد المرضى",
  "Patient Data Management": "إدارة بيانات المرضى",
  "Patient Education": "تثقيف المرضى",
  "Patient-Centered Care": "الرعاية المرتكزة على المريض",
  "Pay-Per-Click Advertising": "إعلانات الدفع لكل نقرة",
  "Payroll Management": "إدارة الرواتب",
  "Payroll Processing": "معالجة الرواتب",
  "Pedagogical Research": "البحث التربوي",
  "Pedagogy": "علم التربية",
  "Pediatric Advanced Life Support": "دعم الحياة المتقدم للأطفال",
  "Pediatric Nursing": "تمريض الأطفال",
  "Pediatric Nutrition": "تغذية الأطفال",
  "Pediatric Occupational Therapy": "العلاج الوظيفي للأطفال",
  "Pediatric Therapy": "العلاج للأطفال",
  "Penetration Testing": "اختبار الاختراق",
  "Performance Coaching": "تدريب الأداء",
  "Performance Improvement": "تحسين الأداء",
  "Performance Improvement Plans": "خطط تحسين الأداء",
  "Performance Management": "إدارة الأداء",
  "Performance Metrics": "مقاييس الأداء",
  "Performance Optimization": "تحسين الأداء",
  "Performance Reporting": "تقرير الأداء",
  "Performance Testing": "اختبار الأداء",
  "Personal Financial Planning": "التخطيط المالي الشخصي","Personal Protective Equipment  Management": "إدارة معدات الحماية الشخصية",
  "Pharmaceutical Manufacturing": "تصنيع الأدوية",
  "Pharmaceutical Marketing": "تسويق الأدوية",
  "Pharmaceutical Patents": "براءات الأدوية",
  "Pharmaceutical Research": "البحث الصيدلاني",
  "Pharmacokinetics": "علم الحرائك الدوائية",
  "Pharmacovigilance": "اليقظة الدوائية",
  "Photography": "التصوير",
  "Picking and Packing Optimization": "تحسين التجميع والتغليف",
  "Podcast Production": "إنتاج البودكاست",
  "Policy Development": "تطوير السياسات",
  "Policy Development and Implementation": "تطوير وتنفيذ السياسات",
  "Policy Implementation": "تنفيذ السياسات",
  "Policy Research": "أبحاث السياسات",
  "Population Health Management": "إدارة صحة السكان",
  "Portfolio Diversification": "تنويع المحفظة الاستثمارية",
  "Portfolio Management": "إدارة المحافظ",
  "Portfolio Rebalancing": "إعادة توازن المحفظة",
  "Positive Attitude": "الموقف الإيجابي",
  "Power BI": "باور بي آي",
  "PowerShell": "باور شيل",
  "Pre-Hospital Care": "الرعاية قبل دخول المستشفى",
  "Predictive Analytics": "التحليلات التنبؤية",
  "Predictive Modeling": "النمذجة التنبؤية",
  "Presentation Skills": "مهارات العرض",
  "Press Release Writing": "كتابة البيانات الصحفية",
  "Pricing Research": "أبحاث التسعير",
  "Print Design": "تصميم المطبوعات",
  "Printmaking": "فن الطباعة",
  "Problem-Solving": "حل المشكلات",
  "Process Improvement": "تحسين العمليات",
  "Procurement Strategies": "استراتيجيات الشراء",
  "Procurement Strategy": "استراتيجية الشراء",
  "Product Demonstrations": "عروض المنتج",
  "Product Development": "تطوير المنتج",
  "Product Knowledge": "معرفة المنتج",
  "Product Launches": "إطلاق المنتجات",
  "Product Lifecycle Management": "إدارة دورة حياة المنتج",
  "Product Management": "إدارة المنتج",
  "Product Roadmapping": "رسم خارطة طريق المنتج",
  "Product Vision and Strategy": "رؤية واستراتيجية المنتج",
  "Professional Development": "التطوير المهني",
  "Profitability Analysis": "تحليل الربحية",
  "Programming Languages": "لغات البرمجة",
  "Project Documentation": "توثيق المشاريع",
  "Project Management": "إدارة المشاريع",
  "Project Planning": "تخطيط المشاريع",
  "Propulsion Systems": "أنظمة الدفع",
  "Prosthetics and Orthotics": "الأطراف الصناعية والتقويمية",
  "Protected Area Management": "إدارة المناطق المحمية",
  "Prototyping": "إنشاء النماذج الأولية",
  "Psychiatric Nursing": "التمريض النفسي",
  "Psychological Testing": "الاختبارات النفسية",
  "Public Administration": "الإدارة العامة",
  "Public Budgeting": "ميزانية القطاع العام",
  "Public Health Nutrition": "تغذية الصحة العامة",
  "Public Policy Evaluation": "تقييم السياسات العامة",
  "Public Relations": "العلاقات العامة",
  "Public Speaking": "الإلقاء العام",
  "PyTorch": "بايتورتش",
  "Python": "بايثون",
  "Python/R Programming": "برمجة بايثون/آر",
  "Quality Assurance": "ضمان الجودة",
  "Quality Assurance Processes": "عمليات ضمان الجودة",
  "Quality Control": "مراقبة الجودة",
  "Quality Control in Pharmaceuticals": "مراقبة الجودة في الصناعات الدوائية",
  "Quantitative Risk Analysis": "تحليل المخاطر الكمي",
  "R": "آر - لغة برمجة",
  "ROS": "نظام تشغيل الروبوتات (ROS)",
  "RPA": "أتمتة العمليات الروبوتية",
  "Rapid Response Team Coordination": "تنسيق فرق الاستجابة السريعة",
  "Real Estate Contracts": "عقود العقارات",
  "Real Estate Law": "قانون العقارات",
  "Recognition Programs": "برامج التقدير",
  "Referral Programs": "برامج الإحالة",
  "Regression Testing": "اختبارات الرجوع",
  "Regulatory Affairs": "الشؤون التنظيمية",
  "Regulatory Affairs in Pharmaceuticals": "الشؤون التنظيمية في الصناعات الدوائية",
  "Regulatory Analysis": "تحليل تنظيمي",
  "Regulatory Change Management": "إدارة التغيرات التنظيمية",
  "Regulatory Compliance": "الامتثال التنظيمي",
  "Regulatory Research": "البحوث التنظيمية",
  "Regulatory Strategy": "الاستراتيجية التنظيمية",
  "Regulatory Submissions": "التقديمات التنظيمية",
  "Rehabilitation Counseling": "إرشاد التأهيل",
  "Rehabilitation Techniques": "تقنيات إعادة التأهيل",
  "Reinforcement Learning": "التعلم المعزز",
  "Relationship Building": "بناء العلاقات",
  "Relationship Management": "إدارة العلاقات",
  "Renewable Energy Financing": "تمويل الطاقة المتجددة",
  "Renewable Energy Policy": "سياسات الطاقة المتجددة",
  "Renewable Energy Project Management": "إدارة مشاريع الطاقة المتجددة",
  "Renewable Energy Solutions": "حلول الطاقة المتجددة",
  "Renewable Energy Systems": "أنظمة الطاقة المتجددة",
  "Renewable Energy and Sustainable Development": "الطاقة المتجددة والتنمية المستدامة",
  "Renewal Sales Strategies": "استراتيجيات تجديد المبيعات",
  "Research Ethics": "أخلاقيات البحث",
  "Research Methodologies": "منهجيات البحث",
  "Resource Allocation": "توزيع الموارد",
  "Retention Strategies": "استراتيجيات الاحتفاظ"

}
